raphaelcodex/__init__.py
raphaelcodex/raphael.py
raphaelcodex/tempCodeRunnerFile.py
raphaelcodex-0.0.1.dist-info/METADATA
raphaelcodex-0.0.1.dist-info/WHEEL
raphaelcodex-0.0.1.dist-info/top_level.txt
raphaelcodex-0.0.1.dist-info/RECORD
